<?xml version="1.0" encoding="UTF-8"?>
<events>
	<event id="p1" >
		<path id="shape" pos="0.43298,0.489945" parent="mainpic" src="shape" fill="4,51,255" fillopacity="0.403285" zpos="0" d="M0.4904 0.2493c-0.0322 0.00292-0.053-0.00226-0.065 0.038c-0.012 0.0403-0.0284 0.0959-0.0451 0.185c-0.0167 0.089-0.0627 0.145-0.0384 0.193c0.0243 0.0474 0.0822 0.0679 0.102 0.0649c0.02-0.00307 0.039-0.0738 0.0582-0.114c0.0192-0.0404 0.0348-0.0952 0.0405-0.133c0.00566-0.0377 0.00466-0.128-0.00383-0.174c-0.00849-0.0462-0.0486-0.0595-0.0486-0.0595Z" />
	</event>
	<event id="p4" >
		<path id="shape" pos="0.490339,0.611829" parent="mainpic" src="shape" fill="4,51,255" fillopacity="0.403285" zpos="0" d="M0.4812 0.3303c-0.03-0.00132-0.0441-0.000797-0.0513 0.0517c-0.00722 0.0525 0.00622 0.111 0.00684 0.185c0.000618 0.074 0.000638 0.235 0.00308 0.281c0.00244 0.0465 0.0206 0.0398 0.0504 0.0392c0.0297-0.000543 0.0576-0.0304 0.0628-0.0639c0.0052-0.0335-0.000861-0.228-0.00746-0.262c-0.0066-0.034-0.0104-0.178-0.0266-0.204c-0.0162-0.0259-0.0377-0.0271-0.0377-0.0271Z" />
	</event>
	<event id="p5" >
		<path id="shape" pos="0.506079,0.507319" parent="mainpic" src="shape" fill="4,51,255" fillopacity="0.403285" zpos="0" d="M0.4951 0.3448c-0.049 0.000966-0.0411-0.00354-0.0409 0.0551c0.000211 0.0586 0.0276 0.184 0.0276 0.184c0 0 0.00869 0.0413 0.0329 0.0719c0.0242 0.0306 0.0352 0.017 0.0402-0.0189c0.00496-0.0359 0.0112-0.0935-0.00189-0.143c-0.0131-0.0497-0.0162-0.0966-0.0334-0.131c-0.0171-0.034-0.0245-0.0179-0.0245-0.0179Z" />
	</event>
	<event id="p8" >
		<path id="shape" pos="0.429163,0.409938" parent="mainpic" src="shape" fill="4,51,255" fillopacity="0.403285" zpos="0" d="M0.3623 0.04711c-0.0873-0.0402-0.0873-0.0402-0.0873-0.0402L0.2798 0.1714c0 0-0.101 0.189-0.0969 0.372c0.00411 0.183 0.0651 0.257 0.125 0.263c0.0594 0.00617 0.122-0.1 0.137-0.117c0.015-0.0166 0.0357-0.123 0.0612-0.151c0.0255-0.0282 0.134-0.103 0.147-0.136c0.0125-0.0325 0.0272-0.12 0.00691-0.178c-0.0203-0.058-0.162-0.207-0.162-0.207L0.3623 0.04711Z" />
	</event>
</events>